{
  "trackers": [
    {
      "type": "unknown",
      "url": "https://stats.iledefrance.fr/piwik.js"
    },
    {
      "type": "unknown",
      "url": "https://stats.iledefrance.fr/piwik.php?action_name=parisregion.eu%2FParis%20Region&idsite=36&rec=1&r=640610&h=1&m=29&s=51&url=https%3A%2F%2Fparisregion.eu%2Fparisregionfp.html%23welcome&_id=e715fb18c17cd466&_idn=0&send_image=0&_refts=0&cookie=1&res=800x600&pv_id=sefopq&pf_net=266&pf_srv=125&pf_tfr=109&pf_dm1=884&uadata=%7B%22fullVersionList%22%3A%5B%5D%2C%22mobile%22%3Afalse%2C%22model%22%3A%22%22%2C%22platform%22%3A%22%22%2C%22platformVersion%22%3A%22%22%7D"
    }
  ],
  "cookies": [
    {
      "name": "_pk_ses.36.60a6",
      "value": "1",
      "domain": ".parisregion.eu",
      "path": "/",
      "expires": 1678586391,
      "size": 16,
      "httpOnly": false,
      "secure": false,
      "session": false,
      "sameSite": "Lax",
      "sameParty": false,
      "sourceScheme": "Secure",
      "sourcePort": 443
    },
    {
      "name": "_pk_id.36.60a6",
      "value": "e715fb18c17cd466.1678584592.",
      "domain": ".parisregion.eu",
      "path": "/",
      "expires": 1712280592,
      "size": 42,
      "httpOnly": false,
      "secure": false,
      "session": false,
      "sameSite": "Lax",
      "sameParty": false,
      "sourceScheme": "Secure",
      "sourcePort": 443
    }
  ],
  "headers": {
    "accept-ranges": "bytes",
    "cache-control": "max-age=0",
    "content-encoding": "gzip",
    "content-length": "10869",
    "content-type": "text/html; charset=utf-8",
    "date": "Sun, 12 Mar 2023 01:29:49 GMT",
    "expires": "Sun, 12 Mar 2023 01:29:49 GMT",
    "last-modified": "Thu, 23 Sep 2021 08:50:17 GMT",
    "strict-transport-security": "max-age=15724800; includeSubDomains",
    "vary": "Accept-Encoding",
    "x-content-type-options": "nosniff",
    "x-frame-options": "sameorigin",
    "x-xss-protection": "1; mode=block"
  },
  "endpoints": [
    {
      "hostname": "parisregion.eu",
      "ip": "217.147.199.227",
      "geoip": {
        "continent": {
          "code": "EU",
          "geoname_id": 6255148,
          "names": {
            "de": "Europa",
            "en": "Europe",
            "es": "Europa",
            "fr": "Europe",
            "ja": "ヨーロッパ",
            "pt-BR": "Europa",
            "ru": "Европа",
            "zh-CN": "欧洲"
          }
        },
        "country": {
          "geoname_id": 3017382,
          "is_in_european_union": true,
          "iso_code": "FR",
          "names": {
            "de": "Frankreich",
            "en": "France",
            "es": "Francia",
            "fr": "France",
            "ja": "フランス共和国",
            "pt-BR": "França",
            "ru": "Франция",
            "zh-CN": "法国"
          }
        },
        "location": {
          "accuracy_radius": 500,
          "latitude": 48.8582,
          "longitude": 2.3387,
          "time_zone": "Europe/Paris"
        },
        "registered_country": {
          "geoname_id": 3017382,
          "is_in_european_union": true,
          "iso_code": "FR",
          "names": {
            "de": "Frankreich",
            "en": "France",
            "es": "Francia",
            "fr": "France",
            "ja": "フランス共和国",
            "pt-BR": "França",
            "ru": "Франция",
            "zh-CN": "法国"
          }
        }
      }
    },
    {
      "hostname": "stats.iledefrance.fr",
      "ip": "109.2.230.239",
      "geoip": {
        "city": {
          "geoname_id": 2986930,
          "names": {
            "en": "Plaisir",
            "fr": "Plaisir"
          }
        },
        "continent": {
          "code": "EU",
          "geoname_id": 6255148,
          "names": {
            "de": "Europa",
            "en": "Europe",
            "es": "Europa",
            "fr": "Europe",
            "ja": "ヨーロッパ",
            "pt-BR": "Europa",
            "ru": "Европа",
            "zh-CN": "欧洲"
          }
        },
        "country": {
          "geoname_id": 3017382,
          "is_in_european_union": true,
          "iso_code": "FR",
          "names": {
            "de": "Frankreich",
            "en": "France",
            "es": "Francia",
            "fr": "France",
            "ja": "フランス共和国",
            "pt-BR": "França",
            "ru": "Франция",
            "zh-CN": "法国"
          }
        },
        "location": {
          "accuracy_radius": 20,
          "latitude": 48.8203,
          "longitude": 1.9497,
          "time_zone": "Europe/Paris"
        },
        "postal": {
          "code": "78370"
        },
        "registered_country": {
          "geoname_id": 3017382,
          "is_in_european_union": true,
          "iso_code": "FR",
          "names": {
            "de": "Frankreich",
            "en": "France",
            "es": "Francia",
            "fr": "France",
            "ja": "フランス共和国",
            "pt-BR": "França",
            "ru": "Франция",
            "zh-CN": "法国"
          }
        },
        "subdivisions": [
          {
            "geoname_id": 3012874,
            "iso_code": "IDF",
            "names": {
              "de": "Île-de-France",
              "en": "Île-de-France",
              "es": "Isla de Francia",
              "fr": "Île-de-France",
              "pt-BR": "Ilha de França"
            }
          },
          {
            "geoname_id": 2967196,
            "iso_code": "78",
            "names": {
              "de": "Yvelines",
              "en": "Yvelines",
              "es": "Yvelines",
              "fr": "Yvelines"
            }
          }
        ]
      }
    }
  ]
}
